{
    "videos": [
        {
            "id": "QpdKIlZglmw",
            "thumbnailURL": "https://i3.ytimg.com/vi/QpdKIlZglmw/maxresdefault.jpg",
            "title": "Top 6 Books to Read on Finance & Business",
            "description": "Watch Shashank Udupa​ reveal his top 6 must-read books for business and finance. Tune in to find out!",
            "categories": ["Personal Finance", "Business", "Books"],
            "channelName": "Avalon Meta Live",
            "channelImageURL": "https://yt3.ggpht.com/ytc/AAUvwngTpfemTxwfewFwmRoyWH_lSBL1FiRtHg32Qno=s48-c-k-c0x00ffffff-no-rj",
            "published_date": "Dec 15, 2020",
            "statistics": {
                "viewCount": 6852,
                "likeCount": 1026,
                "dislikeCount": 10,
                "commentCount": 74
              }
        },
        {
            "id": "FULB3FNSoWQ",
            "thumbnailURL": "https://i3.ytimg.com/vi/FULB3FNSoWQ/maxresdefault.jpg",
            "title": "Banks Suit UP! The Tatas and Birlas are coming for your Money!",
            "description": "Make the trend your friend with tactical advice and insights from Shashank Udupa​.",
            "categories": ["Finance", "Business"],
            "channelName": "Avalon Meta Live",
            "channelImageURL": "https://yt3.ggpht.com/ytc/AAUvwngTpfemTxwfewFwmRoyWH_lSBL1FiRtHg32Qno=s48-c-k-c0x00ffffff-no-rj",
            "published_date": "Nov 24, 2020",
            "statistics": {
                "viewCount": 6852,
                "likeCount": 1026,
                "dislikeCount": 10,
                "commentCount": 74
              }
        },
        {
            "id": "fYhS8MFPiUw",
            "thumbnailURL": "https://i3.ytimg.com/vi/fYhS8MFPiUw/maxresdefault.jpg",
            "title": "Burger King IPO with @Shashank Udupa​ ft. Dr. Elson",
            "description": "In this episode, watch Shashank Udupa​along with Dr. Elson break down the recent Burger King IPO. Disclaimer: We encourage all investors to use the information on the channel as a resource only and should further do their own research on all featured companies, stocks, sectors, markets and information presented on the channel. Nothing published in this video should be considered as investment advice.",
            "categories": ["Finance", "Business", "IPO", "Stock Markets"],
            "channelName": "Avalon Meta Live",
            "channelImageURL": "https://yt3.ggpht.com/ytc/AAUvwngTpfemTxwfewFwmRoyWH_lSBL1FiRtHg32Qno=s48-c-k-c0x00ffffff-no-rj",
            "published_date": "Dec 1, 2020",
            "statistics": {
                "viewCount": 6852,
                "likeCount": 1026,
                "dislikeCount": 10,
                "commentCount": 74
              }
        },
        {
            "id": "qsCUE7kzFHA",
            "thumbnailURL": "https://i3.ytimg.com/vi/qsCUE7kzFHA/maxresdefault.jpg",
            "title": "Investing In Your 20s Simplified - 2021 | Episode 1",
            "description": "In today's episode of World of Finance, we simplify investing for all you 20-year-olds out there. Your 20s are a time for you to start thinking about your future. It's a time where you should start investing but without a job that may be difficult. Today @Shashank Udupa​ will be giving you important tips and tricks so you can secure your financial future. This is an episode you don't want to miss. Watch now!",
            "categories": ["Personal Finance", "Investing", "Investing In Your 20s Simplified", "Psychology of Wealth"],
            "channelName": "Avalon Meta Live",
            "channelImageURL": "https://yt3.ggpht.com/ytc/AAUvwngTpfemTxwfewFwmRoyWH_lSBL1FiRtHg32Qno=s48-c-k-c0x00ffffff-no-rj",
            "published_date": "Feb 16, 2021",
            "statistics": {
                "viewCount": 6852,
                "likeCount": 1026,
                "dislikeCount": 10,
                "commentCount": 74
              }
        },
        {
            "id": "OFxammqEKwg",
            "thumbnailURL": "https://i3.ytimg.com/vi/OFxammqEKwg/maxresdefault.jpg",
            "title": "Investing in Your 20s Simplified | How to Find Growth Stocks with smallcase - Episode 2 | 2021",
            "description": "Investing seems intimidating and difficult. It's something that we all should do to grow our wealth but can seem risky. In today's episode of World of Finance, we talk about smallcase and investment options for everyone. @Shashank Udupa​ creates his own smallcases and teaches you how to adjust them to fit your budget and risk. This is one episode that'll greatly help your investment journey. Watch now!",
            "categories": ["Personal Finance", "Investing", "Investing In Your 20s Simplified"],
            "channelName": "Avalon Meta Live",
            "channelImageURL": "https://yt3.ggpht.com/ytc/AAUvwngTpfemTxwfewFwmRoyWH_lSBL1FiRtHg32Qno=s48-c-k-c0x00ffffff-no-rj",
            "published_date": "Feb 23, 2021",
            "statistics": {
                "viewCount": 6852,
                "likeCount": 1026,
                "dislikeCount": 10,
                "commentCount": 74
              }
        },
        {
            "id": "rT-kPOy4irM",
            "thumbnailURL": "https://i3.ytimg.com/vi/rT-kPOy4irM/maxresdefault.jpg",
            "title": "Investing In 20s Simplified | Top 3 Tools For Fundamental Analysis Of Growth Stocks - Ep. 3 | 2021",
            "description": "Picking stocks can be done in a lot of ways. But businesses and companies are based in fundamentals.  These principles can help  you choose the best from the rest. In today's episode, @Shashank Udupa​ looks at 3 different ways to analyze stocks. The different rules behind stock analysis and more! This brings an end to our three-part series on trading, so be sure to watch this!",
            "categories": ["Personal Finance", "Investing", "Investing In Your 20s Simplified"],
            "channelName": "Avalon Meta Live",
            "channelImageURL": "https://yt3.ggpht.com/ytc/AAUvwngTpfemTxwfewFwmRoyWH_lSBL1FiRtHg32Qno=s48-c-k-c0x00ffffff-no-rj",
            "published_date": "Mar 2, 2021",
            "statistics": {
                "viewCount": 6852,
                "likeCount": 1026,
                "dislikeCount": 10,
                "commentCount": 74
              }
        },
        {
            "id": "LwuHJ6BCiSs",
            "thumbnailURL": "https://i3.ytimg.com/vi/LwuHJ6BCiSs/maxresdefault.jpg",
            "title": "What To Expect From Budget 2021? (And Why You Should Care)",
            "description": "The finance minister's announcement that budget 2021 will be like no other has created a lot of excitement among citizens. Citizens hope and expect a lot from the government. However, there are undeniable places the government will have to spend. On Healthcare, Infrastructure, Market stimulus, etc. There is going to be a lot to look forward to. Watch now to take a look at the expectations of Indian citizens from the Union Budget 2021 in today's episode of World of Finance with @Shashank Udupa​ ",
            "categories": ["Finance", "Budget", "Business", "Stock Markets"],
            "channelName": "Avalon Meta Live",
            "channelImageURL": "https://yt3.ggpht.com/ytc/AAUvwngTpfemTxwfewFwmRoyWH_lSBL1FiRtHg32Qno=s48-c-k-c0x00ffffff-no-rj",
            "published_date": "Jan 26, 2021",
            "statistics": {
                "viewCount": 6852,
                "likeCount": 1026,
                "dislikeCount": 10,
                "commentCount": 74
              }
        },
        {
            "id": "wwWf2sNxEKQ&",
            "thumbnailURL": "https://i3.ytimg.com/vi/wwWf2sNxEKQ&/maxresdefault.jpg",
            "title": "Budget 2021 India - Is it good for you?",
            "description": "The Budget 2021 was set to be the most promising one for India. A lot was on the line from coming back from a negative GDP to battling COVID and political pressure this was a budget that needed to be steady and not rock the boat. The Indian economy was hit hard last year and this budget had a lot on the line. Last week we put out a video on the expectations of the Budget. Today we'll be discussing the Budget 2021. Tune into find on today's episode of World of Finance with @Shashank Udupa​ ",
            "categories": ["Finance", "Budget", "Business", "Stock Markets"],
            "channelName": "Avalon Meta Live",
            "channelImageURL": "https://yt3.ggpht.com/ytc/AAUvwngTpfemTxwfewFwmRoyWH_lSBL1FiRtHg32Qno=s48-c-k-c0x00ffffff-no-rj",
            "published_date": "Feb 2, 2021",
            "statistics": {
                "viewCount": 6852,
                "likeCount": 1026,
                "dislikeCount": 10,
                "commentCount": 74
              }
        },
        {
            "id": "rU8mVb_bc-M",
            "thumbnailURL": "https://i3.ytimg.com/vi/rU8mVb_bc-M/maxresdefault.jpg",
            "title": "Bitcoin. Boom or Bubble?",
            "description": "On today's Tuesday Finance Live, Shashank Udupa dives deep into the world of #Bitcoin​ and #Cryptocurrency​. Watch as he explains the sudden rise in value for Bitcoin and what this could mean for the future of crypto.",
            "categories": ["Finance", "Business", "Bitcoin", "Cryptocurrency"],
            "channelName": "Avalon Meta Live",
            "channelImageURL": "https://yt3.ggpht.com/ytc/AAUvwngTpfemTxwfewFwmRoyWH_lSBL1FiRtHg32Qno=s48-c-k-c0x00ffffff-no-rj",
            "published_date": "Dec 22, 2020",
            "statistics": {
                "viewCount": 6852,
                "likeCount": 1026,
                "dislikeCount": 10,
                "commentCount": 74
              }
        },
        {
            "id": "R7b_VzfVmb0",
            "thumbnailURL": "https://i3.ytimg.com/vi/R7b_VzfVmb0/maxresdefault.jpg",
            "title": "Elon Buys Bitcoin, Dogecoin Up - What's Happening?",
            "description": "Elon Musk has gotten a reputation for supporting, promoting and raising crypto more than ever this past year. Lately he's been tweeting a tonne about Doge Coin. But this move by his company Tesla may be his  biggest show of support for crypto yet. Yesterday Feb 9th, Tesla invested a massive 1.5 billion in bitcoin. He's also gone on the record saying they will accept the coin as payment in the future as well. In today's episode of World of Finance with @Shashank Udupa​ , we talk about why this is such a big deal and what this could mean for cryptocurrency in the future.",
            "categories": ["Finance", "Business", "Bitcoin", "Cryptocurrency"],
            "channelName": "Avalon Meta Live",
            "channelImageURL": "https://yt3.ggpht.com/ytc/AAUvwngTpfemTxwfewFwmRoyWH_lSBL1FiRtHg32Qno=s48-c-k-c0x00ffffff-no-rj",
            "published_date": "Feb 9, 2021",
            "statistics": {
                "viewCount": 6852,
                "likeCount": 1026,
                "dislikeCount": 10,
                "commentCount": 74
              }
        },
        {
            "id": "xW-AG1uGeBg",
            "thumbnailURL": "https://i3.ytimg.com/vi/xW-AG1uGeBg/maxresdefault.jpg",
            "title": "Back to Basics - Let's Begin!",
            "description": "The stock market has been weird lately and what better time to brush up on the fundamentals. In today's video we dive back into the basics of stock market",
            "categories": ["Finance", "Stock Markets", "Stock Market Basics"],
            "channelName": "Shashank Udupa",
            "channelImageURL": "https://yt3.ggpht.com/ytc/AAUvwngcam1qyJtXZSiM5ok78HKog6FVlMBPqd6dM01fGQ=s48-c-k-c0x00ffffff-no-rj",
            "published_date": "Apr 1, 2021",
            "statistics": {
                "viewCount": 6852,
                "likeCount": 1026,
                "dislikeCount": 10,
                "commentCount": 74
              }
        },
        {
            "id": "mvaPJuEUqWI",
            "thumbnailURL": "https://i3.ytimg.com/vi/mvaPJuEUqWI/maxresdefault.jpg",
            "title": "Top Personal Finance Rules To Follow in 2021",
            "description": "Personal finance is a term that covers managing your money as well as saving and investing. It is about meeting personal financial goals, whether it’s having enough for short-term financial needs, planning for retirement, or saving for your child’s college education. Watch the entire video to learn more.",
            "categories": ["Finance", "Personal Finance", "Personal Finance Basics"],
            "channelName": "Shashank Udupa",
            "channelImageURL": "https://yt3.ggpht.com/ytc/AAUvwngcam1qyJtXZSiM5ok78HKog6FVlMBPqd6dM01fGQ=s48-c-k-c0x00ffffff-no-rj",
            "published_date": "Apr 3, 2021",
            "statistics": {
                "viewCount": 6852,
                "likeCount": 1026,
                "dislikeCount": 10,
                "commentCount": 74
              }
        }
    ]
    }